<?xml version="1.0"?>
<AIServerConfiguration xmlns:xsi="http://www.w3.org/2001/XMLSchema-instance" xmlns:xsd="http://www.w3.org/2001/XMLSchema">
  <ExternalAIProviders>true</ExternalAIProviders>
  <AITools>
    <AIToolConfiguration>
      <GUID>975395e7-8f7f-47a8-84a7-dbf7bb3bec44</GUID>
      <Name>database_execute_query</Name>
      <Description>Executes a SQL SELECT statement against a data source and returns up to 50 rows as a tab-separated table. Use it to validate generated SQL, check sample data, debug wrong results, or preview table contents. Pass datasource_guid (and optionally connection_guid) as returned by datasource_list to target a specific source or connection.</Description>
      <ParametersSchema>{"type":"object","properties":{"sql":{"type":"string","description":"SQL SELECT statement to execute"},"datasource_guid":{"type":"string","description":"GUID of the data source to query, as returned by datasource_list. Omit to use the default source."},"connection_guid":{"type":"string","description":"GUID of the connection to use, as returned by datasource_list. Omit to use the source default connection."}},"required":["sql"]}</ParametersSchema>
      <ExecutionScriptFile>database_execute_query.cshtml</ExecutionScriptFile>
    </AIToolConfiguration>
    <AIToolConfiguration>
      <GUID>f56c62db-9a53-413e-8df4-6dde496adff4</GUID>
      <Name>database_get_columns</Name>
      <Description>Returns the column names and data types of a table. Use it to confirm column names before generating report elements, or to discover schema when scanning a data source. Pass datasource_guid (and optionally connection_guid) as returned by datasource_list to target a specific source or connection.</Description>
      <ParametersSchema>{"type":"object","properties":{"table":{"type":"string","description":"Table name, optionally schema-qualified (e.g. dbo.Orders)"},"datasource_guid":{"type":"string","description":"GUID of the data source, as returned by datasource_list. Omit to use the default source."},"connection_guid":{"type":"string","description":"GUID of the connection to use, as returned by datasource_list. Omit to use the source default connection."}},"required":["table"]}</ParametersSchema>
      <ExecutionScriptFile>database_get_columns.cshtml</ExecutionScriptFile>
    </AIToolConfiguration>
    <AIToolConfiguration>
      <GUID>3f576977-b633-4b1c-80ee-a2e2d015c13d</GUID>
      <Name>database_get_sample_values</Name>
      <Description>Returns up to 50 distinct non-null values from the given column. Use it to discover what enum or category values exist when building restriction filters or display labels. Pass datasource_guid (and optionally connection_guid) as returned by datasource_list to target a specific source or connection.</Description>
      <ParametersSchema>{"type":"object","properties":{"table":{"type":"string","description":"Table name"},"column":{"type":"string","description":"Column name"},"datasource_guid":{"type":"string","description":"GUID of the data source, as returned by datasource_list. Omit to use the default source."},"connection_guid":{"type":"string","description":"GUID of the connection to use, as returned by datasource_list. Omit to use the source default connection."}},"required":["table","column"]}</ParametersSchema>
      <ExecutionScriptFile>database_get_sample_values.cshtml</ExecutionScriptFile>
    </AIToolConfiguration>
    <AIToolConfiguration>
      <GUID>84ddf1ed-6473-488a-90a4-2dee3205e7ea</GUID>
      <Name>database_count_rows</Name>
      <Description>Returns the row count of a table, optionally filtered by a WHERE clause. Use it to decide whether TopRecords makes sense or to check the cardinality of a filter before applying it. Pass datasource_guid (and optionally connection_guid) as returned by datasource_list to target a specific source or connection.</Description>
      <ParametersSchema>{"type":"object","properties":{"table":{"type":"string","description":"Table name"},"where":{"type":"string","description":"Optional SQL WHERE clause without the WHERE keyword (e.g. Country = 'France')"},"datasource_guid":{"type":"string","description":"GUID of the data source, as returned by datasource_list. Omit to use the default source."},"connection_guid":{"type":"string","description":"GUID of the connection to use, as returned by datasource_list. Omit to use the source default connection."}},"required":["table"]}</ParametersSchema>
      <ExecutionScriptFile>database_count_rows.cshtml</ExecutionScriptFile>
    </AIToolConfiguration>
    <AIToolConfiguration>
      <GUID>21865749-3026-4f91-8b66-17d25cfc5d81</GUID>
      <Name>datasource_list</Name>
      <Description>Lists all configured data sources with their GUID, database type, available connections (each with its GUID), and tables. Call this first to discover which sources, connections, and tables are available before querying or inspecting them. Use the returned GUIDs with datasource_guid and connection_guid parameters in database tools.</Description>
      <ExecutionScriptFile>datasource_list.cshtml</ExecutionScriptFile>
    </AIToolConfiguration>
    <AIToolConfiguration>
      <GUID>c3f46643-52cc-4570-b580-c2b787bb4de9</GUID>
      <Name>datasource_get_detail</Name>
      <Description>Returns a structured summary of a data source: connection info (no credentials), tables with their columns and types, and joins between tables. Use this to understand the schema and relationships before writing SQL.</Description>
      <ParametersSchema>{"type":"object","properties":{"name":{"type":"string","description":"Data source name"}},"required":["name"]}</ParametersSchema>
      <ExecutionScriptFile>datasource_get_detail.cshtml</ExecutionScriptFile>
    </AIToolConfiguration>
    <AIToolConfiguration>
      <GUID>40051ada-ebee-4e40-8264-472186877f64</GUID>
      <Name>report_get_detail</Name>
      <Description>Returns full details of a report: display name, description, and for each model its source, elements (columns with pivot position and aggregate), and restrictions (with prompt and required flags). Pass the relative path as returned by report_list (e.g. Reports\Sales\monthly.srex or Personal\username\monthly.srex).</Description>
      <ParametersSchema>{"type":"object","properties":{"path":{"type":"string","description":"Relative report path as returned by report_list (e.g. Reports\\Sales\\monthly.srex)"}},"required":["path"]}</ParametersSchema>
      <ExecutionScriptFile>report_get_detail.cshtml</ExecutionScriptFile>
    </AIToolConfiguration>
    <AIToolConfiguration>
      <GUID>5329983b-9c8a-4825-b51d-9a7fb4949b53</GUID>
      <Name>report_get_xml</Name>
      <Description>Returns the raw XML content of a report file. Use this to inspect the full report definition or to obtain a template before modifying and saving it with report_create_from_sql. Pass the relative path as returned by report_list (e.g. Reports\Sales\monthly.srex or Personal\username\monthly.srex).</Description>
      <ParametersSchema>{"type":"object","properties":{"path":{"type":"string","description":"Relative report path as returned by report_list (e.g. Reports\\Sales\\monthly.srex)"}},"required":["path"]}</ParametersSchema>
      <ExecutionScriptFile>report_get_xml.cshtml</ExecutionScriptFile>
    </AIToolConfiguration>
    <AIToolConfiguration>
      <GUID>174f7dee-ff46-4053-bce3-85355f55f9df</GUID>
      <Name>report_check_model_type</Name>
      <Description>Analyses a report request and returns whether it requires a SQL model (report_create_from_sql) or a metadata model (report_create_from_xml), with the reasoning. Always call this before creating any report.</Description>
      <ParametersSchema>{"type":"object","properties":{"request":{"type":"string","description":"The user's report request, exactly as stated."}},"required":["request"]}</ParametersSchema>
      <ExecutionScriptFile>report_check_model_type.cshtml</ExecutionScriptFile>
    </AIToolConfiguration>
    <AIToolConfiguration>
      <GUID>aa2baa07-6828-4f6c-9640-466feb5e1b22</GUID>
      <Name>report_create_from_sql</Name>
      <Description>Creates a new report with a single SQL model using the Seal Report API. The SQL is executed at runtime against the chosen data source; columns are resolved dynamically so no metadata GUIDs are required. Use datasource_get_detail to obtain the correct table and column names before writing the SQL.</Description>
      <ParametersSchema>{"type":"object","properties":{"path":{"type":"string","description":"Destination relative path (e.g. Reports\\Sales\\new_report.srex). Root prefix (Reports or Personal) determines the folder; defaults to Reports root if omitted."},"display_name":{"type":"string","description":"Report display name shown in results."},"sql":{"type":"string","description":"SELECT statement executed by the model."},"source_guid":{"type":"string","description":"GUID of the data source to use, as returned by datasource_list or datasource_get_detail. Omit to use the default source."},"model_name":{"type":"string","description":"Optional name for the model. Defaults to 'Model'."},"description":{"type":"string","description":"Optional report description stored in MetaInfo."},"keep_column_names":{"type":"boolean","description":"If true, SQL column aliases are used as-is for column headers. Default false."},"overwrite":{"type":"boolean","description":"If true, overwrites an existing file. Default false."}},"required":["path","display_name","sql"]}</ParametersSchema>
      <ExecutionScriptFile>report_create_from_sql.cshtml</ExecutionScriptFile>
    </AIToolConfiguration>
    <AIToolConfiguration>
      <GUID>25cd0ba3-0d19-4cc8-a5ae-aba7b4e750f2</GUID>
      <Name>report_create_from_xml</Name>
      <Description>Creates a new metadata report by writing a complete XML definition. Use for reports built on the data source's defined metadata columns (tabular, pivot, search reports). Before calling this tool, set &lt;MetaSourceGUID&gt; to the GUID from datasource_list and every &lt;MetaColumnGUID&gt; to the matching column GUID from datasource_get_detail. Internal cross-reference GUIDs (GUID, ViewGUID, SourceGUID, ModelGUID) are regenerated automatically; metadata reference GUIDs (MetaSourceGUID, MetaColumnGUID) are preserved exactly as supplied. For SQL-based reports use report_create_from_sql instead.</Description>
      <ParametersSchema>{"type":"object","properties":{"path":{"type":"string","description":"Destination relative path (e.g. Reports\\\\Sales\\\\new_report.srex). Root prefix (Reports or Personal) determines the folder; defaults to Reports root if omitted."},"xml":{"type":"string","description":"Complete XML content of the report file (.srex). Retrieve a template via report_get_xml, replace MetaSourceGUID and MetaColumnGUID with values from datasource_list / datasource_get_detail, then pass the result here."},"overwrite":{"type":"boolean","description":"If true, overwrites an existing file at the destination path. Default false."}},"required":["path","xml"]}</ParametersSchema>
      <ExecutionScriptFile>report_create_from_xml.cshtml</ExecutionScriptFile>
    </AIToolConfiguration>
    <AIToolConfiguration>
      <GUID>f1a2b3c4-d5e6-4f7a-8b9c-0d1e2f3a4b5c</GUID>
      <Name>report_configure_output</Name>
      <Description>Configures or removes an output on an existing report. Use action=configure (default) to add or update a delivery output; device_type selects the delivery method: folder (default), email, or ftp. Use action=delete to remove outputs and all their associated schedules — never use file_manage for this. Pass output_guid to target a specific output for update or delete; for folder outputs without a GUID the first folder output is reused. For delete: pass output_guid or output_name to remove a specific output; omit both to delete all. Returns outputGUID in the result — store it to pass to report_configure_schedule. Always call this before report_configure_schedule.</Description>
      <ParametersSchema>{"type":"object","properties":{"path":{"type":"string","description":"Relative report path as returned by report_list (e.g. Reports\\Sales\\monthly.srex)"},"action":{"type":"string","enum":["configure","delete"],"description":"configure (default): add or update an output. delete: remove the output and all its linked schedules from the report (does NOT delete the report file)."},"device_type":{"type":"string","enum":["folder","email","ftp"],"description":"Delivery type: folder (default), email, or ftp."},"output_guid":{"type":"string","description":"GUID of an existing output to update or delete, as returned by a prior call. Use to target a specific output when the report has multiple."},"output_name":{"type":"string","description":"For action=configure: display name for this output (auto-generated if omitted). For action=delete: name of the specific output to remove. Omit to delete all outputs on the report."},"device_name":{"type":"string","description":"Name of the specific email or FTP device to use when multiple are configured."},"folder_path":{"type":"string","description":"Required for device_type=folder; optional for device_type=ftp. For folder: 'Personal' or 'Personal\\subfolder' for personal folder; 'Reports\\subfolder' for a repository folder; absolute path (e.g. C:\\Reports\\Daily); or path with %SEALREPOSITORY%. For ftp: the remote directory on the file server (default '/')."},"file_name":{"type":"string","description":"Output file name template. Use {0:yyyyMMdd} for the execution date. Omit to use the report display name. Never include a file extension."},"output_format":{"type":"string","enum":["html","pdf","Excel","csv","Text","XML","Json"],"description":"Output file format. Default is Excel."},"email_to":{"type":"string","description":"Required for device_type=email. Recipient email address(es), semicolon-separated."},"email_cc":{"type":"string","description":"CC email address(es), semicolon-separated."},"email_bcc":{"type":"string","description":"BCC email address(es), semicolon-separated."},"email_subject":{"type":"string","description":"Email subject line. Defaults to the report name."},"email_body":{"type":"string","description":"Plain-text or HTML body for the email."},"email_html_body":{"type":"boolean","description":"If true, sends the report HTML as the email body (no attachment)."},"email_skip_attachments":{"type":"boolean","description":"If true, sends the email body only with no file attached."}},"required":["path"]}</ParametersSchema>
      <ExecutionScriptFile>report_configure_output.cshtml</ExecutionScriptFile>
    </AIToolConfiguration>
    <AIToolConfiguration>
      <GUID>a2b3c4d5-e6f7-4a8b-9c0d-1e2f3a4b5c6d</GUID>
      <Name>report_configure_schedule</Name>
      <Description>Adds, updates, or removes a recurring or one-time schedule on an existing report's output. Use action=configure (default) to add a new schedule, or pass schedule_guid to update an existing one. Use action=delete with schedule_guid (preferred) or schedule_name to remove a specific schedule — never use file_manage for this, and never omit both targets. Requires the report to already have an output — call report_configure_output first if none exists. By default the schedule attaches to the first folder output; pass output_guid (as returned by report_configure_output) to bind it to a specific output such as an FTP or email output. Returns scheduleGUID in the result — store it to later modify or delete this schedule. Schedule GUIDs can also be discovered via report_list. Use when the user wants automated execution: "every morning at 7am", "weekly on Monday", "run daily", "schedule this report", "send every month on the 1st", "delete the schedule".</Description>
      <ParametersSchema>{"type":"object","properties":{"path":{"type":"string","description":"Relative report path as returned by report_list (e.g. Reports\\Sales\\monthly.srex)"},"action":{"type":"string","enum":["configure","delete"],"description":"configure (default): add a new schedule, or update an existing one when schedule_guid is provided. delete: remove the schedule identified by schedule_guid or schedule_name (does NOT delete the report file or its output)."},"schedule_guid":{"type":"string","description":"GUID of an existing schedule, as returned by a prior call or by report_list. Required to update a schedule; for delete, pass this (preferred) or schedule_name to target a specific schedule."},"output_guid":{"type":"string","description":"GUID of the output to attach this schedule to, as returned by report_configure_output. Omit to use the first folder output. Pass it to schedule a specific output such as an FTP or email output."},"type":{"type":"string","enum":["daily","weekly","monthly","once"],"description":"Required for action=configure. Recurrence type. Use once for a single one-time run."},"start_datetime":{"type":"string","description":"Required for action=configure. ISO 8601 date-time for the first or only run, e.g. 2025-06-01T07:00:00"},"days_interval":{"type":"integer","description":"For daily: interval in days between runs (default 1 = every day)."},"weekdays":{"type":"array","items":{"type":"integer"},"description":"For weekly: days of week to run. 0=Sunday, 1=Monday … 6=Saturday. E.g. [1,3] = Mon and Wed."},"months":{"type":"array","items":{"type":"integer"},"description":"For monthly: months to run (1=Jan … 12=Dec). Omit for every month."},"days":{"type":"array","items":{"type":"integer"},"description":"For monthly: days of month to run (1-31, 32=last day). E.g. [1] = 1st of each month."},"schedule_name":{"type":"string","description":"For action=configure: display name for the schedule (auto-generated if omitted). For action=delete: name of the specific schedule to remove when schedule_guid is not provided."}},"required":["path"]}</ParametersSchema>
      <ExecutionScriptFile>report_configure_schedule.cshtml</ExecutionScriptFile>
    </AIToolConfiguration>
    <AIToolConfiguration>
      <GUID>d4e5f6a7-b8c9-4d0e-1f2a-3b4c5d6e7f80</GUID>
      <Name>report_execute_get_data</Name>
      <Description>Executes a report and returns its result tables as structured JSON data, followed by the execution messages. Use it to fetch the actual data produced by an existing report for analysis, answering data questions, generating a summary, or diagnosing execution issues. Pass the relative path as returned by report_list (e.g. Reports\Sales\monthly.srex). Optionally pass model_name to restrict the output to a single model.</Description>
      <ParametersSchema>{"type":"object","properties":{"path":{"type":"string","description":"Relative report path as returned by report_list (e.g. Reports\\Sales\\monthly.srex or Personal\\username\\monthly.srex)"},"model_name":{"type":"string","description":"Optional model name to restrict results to a single model. If omitted, all models are returned."}},"required":["path"]}</ParametersSchema>
      <ExecutionScriptFile>report_execute_get_data.cshtml</ExecutionScriptFile>
    </AIToolConfiguration>
    <AIToolConfiguration>
      <GUID>e7d2c9a4-1b6f-4e83-9a2c-5f0d8b3e7c61</GUID>
      <Name>file_list</Name>
      <Description>Browses files in the folders the current user has access to, across the Reports and Personal roots. Returns relative paths in the same format file_manage expects (e.g. Reports\Sales\monthly.srex, Personal\user\notes.txt) together with size and last-modified date. Lists every file type, not only reports, and includes files-only folders. ALWAYS call this tool first to discover and confirm the exact path of a file before any file_manage operation (delete, rename, move, copy). Optionally filter by sub-folder name(s) via 'folders', or by file extension via 'extension'.</Description>
      <ParametersSchema>{"type":"object","properties":{"folders":{"type":"array","items":{"type":"string"},"description":"Optional list of sub-folder names to restrict the scan. Omit or pass [] to scan everything accessible."},"extension":{"type":"string","description":"Optional file extension filter without the dot, e.g. 'srex' or 'txt'. Omit to list all files."}}}</ParametersSchema>
      <ExecutionScriptFile>file_list.cshtml</ExecutionScriptFile>
    </AIToolConfiguration>
    <AIToolConfiguration>
      <GUID>c3b1942e-fa0b-48c5-84f1-dc19709d4e07</GUID>
      <Name>file_manage</Name>
      <Description>File-level operations on a file in the repository: delete, rename (new filename in the same folder), move (to a different folder or root), or copy (to a new path). Works on any repository file (reports .srex, etc.). Paths use the format returned by report_list, e.g. Reports\Sales\monthly.srex. Roots are: Reports, Personal. Access is restricted to files within these roots and to folders the current user has rights on. Always call file_list first to discover and confirm the exact source path before performing any file_manage operation.</Description>
      <ParametersSchema>{"type":"object","properties":{"action":{"type":"string","enum":["delete","rename","move","copy"],"description":"Operation to perform"},"path":{"type":"string","description":"Relative path of the source report (e.g. Reports\\Sales\\monthly.srex)"},"destination":{"type":"string","description":"Target relative path for rename/move/copy (e.g. Reports\\Archive\\monthly.srex). Not used for delete."}},"required":["action","path"]}</ParametersSchema>
      <ExecutionScriptFile>file_manage.cshtml</ExecutionScriptFile>
    </AIToolConfiguration>
    <AIToolConfiguration>
      <GUID>89394f6c-c895-4d8b-8ced-a0864cdec1d7</GUID>
      <Name>report_list</Name>
      <Description>Lists reports accessible to the current web user. Only folders with access rights are browsed — hidden folders (right=0) and files-only folders are excluded — and Personal folders are included when the user has personal folder rights. Display paths use "Reports\..." or "Personal\username\..." format compatible with other report tools. Pass an optional list of sub-folder names to restrict the scan; omit or pass [] to scan all accessible folders.</Description>
      <ParametersSchema>{"type":"object","properties":{"folders":{"type":"array","items":{"type":"string"},"description":"Optional list of sub-folder names to scan. Omit or pass [] to scan everything accessible."}}}</ParametersSchema>
      <ExecutionScriptFile>report_list.cshtml</ExecutionScriptFile>
    </AIToolConfiguration>
    <AIToolConfiguration>
      <GUID>b3c7f2a1-4d8e-4f9b-a2c5-e6d1f0b3a8c4</GUID>
      <Name>get_current_folder</Name>
      <Description>Returns the user's current working folder — the folder the user is currently browsing in the web interface — in the display-path format used by report_list and the report creation tools (e.g. "Reports\Sales"). Also lists all folders where the user has write access. Always call this tool fresh every time you need the current folder; never reuse a result from earlier in the conversation, as the user may have navigated to a different folder since then.</Description>
      <ParametersSchema>{"type":"object","properties":{}}</ParametersSchema>
      <ExecutionScriptFile>get_current_folder.cshtml</ExecutionScriptFile>
    </AIToolConfiguration>
    <AIToolConfiguration>
      <GUID>a8b9c0d1-e2f3-4a4b-5c6d-7e8f9a0b1c2d</GUID>
      <Name>log_read</Name>
      <Description>Reads Seal Report log files for the given date. Type must be one of: events (server start/stop, authentication, errors), executions (report execution traces), schedules (scheduler runs). Date defaults to today. Use keyword to filter lines containing a specific string. Returns up to max_lines lines (default 200).</Description>
      <ParametersSchema>{"type":"object","properties":{"type":{"type":"string","enum":["events","executions","schedules"],"description":"Log file type: events, executions or schedules"},"date":{"type":"string","description":"Date in YYYY-MM-DD format. Defaults to today."},"keyword":{"type":"string","description":"Optional string filter: only lines containing this keyword (case-insensitive) are returned."},"max_lines":{"type":"integer","description":"Maximum number of lines to return. Defaults to 200."}},"required":["type"]}</ParametersSchema>
      <ExecutionScriptFile>log_read.cshtml</ExecutionScriptFile>
    </AIToolConfiguration>
    <AIToolConfiguration>
      <GUID>1f2e3d4c-5b6a-4798-8c0d-1e2f3a4b5c6e</GUID>
      <Name>view_get_parameters</Name>
      <Description>Lists the configurable rendering parameters of a report's view (e.g. the "Chart JS" view), with each parameter's type, current value, default, allowed values and description. Call with only 'path' to list every view in the report; then call again with view_name (e.g. "Chart JS") to see that view's parameters. Use this before report_configure_view to discover valid parameter names and values. Read-only.</Description>
      <ParametersSchema>{"type":"object","properties":{"path":{"type":"string","description":"Relative report path as returned by report_list (e.g. Reports\\Sales\\monthly.srex)"},"view_name":{"type":"string","description":"Name of the view to inspect (e.g. 'Chart JS', 'Page Table'). Omit to list all views in the report."},"template_name":{"type":"string","description":"Optional template name filter (e.g. 'Chart JS') when several views share a name."}},"required":["path"]}</ParametersSchema>
      <ExecutionScriptFile>view_get_parameters.cshtml</ExecutionScriptFile>
    </AIToolConfiguration>
    <AIToolConfiguration>
      <GUID>2a3b4c5d-6e7f-4890-9a1b-2c3d4e5f6a7b</GUID>
      <Name>report_configure_view</Name>
      <Description>Sets one or more rendering parameters on an existing report's view, in place, without rewriting the report. Use it to change how a view renders - for example to make a Chart JS view horizontal and stacked (chartjs_bar_horizontal=True, chartjs_bar_stacked=True), hide a legend, set a chart title, or switch a pie to a doughnut. Always call view_get_parameters first to discover valid parameter names and allowed values for the target view. Values are validated against each parameter's type and enumeration; parameters left at their default are not stored. For stacked bar charts the model must have a series Splitter (a Column element), otherwise there is a single series and nothing stacks.</Description>
      <ParametersSchema>{"type":"object","properties":{"path":{"type":"string","description":"Relative report path as returned by report_list (e.g. Reports\\Sales\\monthly.srex)"},"view_name":{"type":"string","description":"Name of the view to configure (e.g. 'Chart JS'). Required unless template_name is given."},"template_name":{"type":"string","description":"Template name of the view to configure (e.g. 'Chart JS'), used instead of or together with view_name to disambiguate."},"parameters":{"type":"object","description":"Object of parameter name/value pairs to set, e.g. {\"chartjs_bar_horizontal\":\"True\",\"chartjs_bar_stacked\":\"True\"}. Use view_get_parameters to discover valid names and values. Booleans are 'True'/'False'.","additionalProperties":{"type":"string"}}},"required":["path","parameters"]}</ParametersSchema>
      <ExecutionScriptFile>report_configure_view.cshtml</ExecutionScriptFile>
    </AIToolConfiguration>
  </AITools>
  <DefaultProviderGUID />
  <DefaultAgentGUID>c3d4e5f6-a7b8-4c9d-0e1f-2a3b4c5d6e7f</DefaultAgentGUID>
  <AIAgents>
    <AIAgentConfiguration>
      <GUID>a1b2c3d4-e5f6-4a7b-8c9d-0e1f2a3b4c5d</GUID>
      <Name>Report Designer</Name>
      <Description>Designs and builds reports from natural-language requests: explores data sources, validates SQL, and creates SQL-based or metadata-based reports.</Description>
      <ProviderGUID>1</ProviderGUID>
      <ToolGUIDs>
        <GUID>975395e7-8f7f-47a8-84a7-dbf7bb3bec44</GUID>
        <GUID>f56c62db-9a53-413e-8df4-6dde496adff4</GUID>
        <GUID>3f576977-b633-4b1c-80ee-a2e2d015c13d</GUID>
        <GUID>84ddf1ed-6473-488a-90a4-2dee3205e7ea</GUID>
        <GUID>21865749-3026-4f91-8b66-17d25cfc5d81</GUID>
        <GUID>c3f46643-52cc-4570-b580-c2b787bb4de9</GUID>
        <GUID>40051ada-ebee-4e40-8264-472186877f64</GUID>
        <GUID>5329983b-9c8a-4825-b51d-9a7fb4949b53</GUID>
        <GUID>174f7dee-ff46-4053-bce3-85355f55f9df</GUID>
        <GUID>aa2baa07-6828-4f6c-9640-466feb5e1b22</GUID>
        <GUID>25cd0ba3-0d19-4cc8-a5ae-aba7b4e750f2</GUID>
        <GUID>d4e5f6a7-b8c9-4d0e-1f2a-3b4c5d6e7f80</GUID>
        <GUID>e7d2c9a4-1b6f-4e83-9a2c-5f0d8b3e7c61</GUID>
        <GUID>c3b1942e-fa0b-48c5-84f1-dc19709d4e07</GUID>
        <GUID>89394f6c-c895-4d8b-8ced-a0864cdec1d7</GUID>
        <GUID>b3c7f2a1-4d8e-4f9b-a2c5-e6d1f0b3a8c4</GUID>
        <GUID>1f2e3d4c-5b6a-4798-8c0d-1e2f3a4b5c6e</GUID>
        <GUID>2a3b4c5d-6e7f-4890-9a1b-2c3d4e5f6a7b</GUID>
      </ToolGUIDs>
      <DefaultSystemPrompt />
      <SystemPromptFile>designer-system-prompt.md</SystemPromptFile>
      <SamplePromptsFile>designer-sample-prompts.md</SamplePromptsFile>
    </AIAgentConfiguration>
    <AIAgentConfiguration>
      <GUID>b2c3d4e5-f6a7-4b8c-9d0e-1f2a3b4c5d6e</GUID>
      <Name>Schedule &amp; Output</Name>
      <Description>Configures report delivery and automation: sets up folder, email, and FTP outputs and manages recurring or one-time execution schedules.</Description>
      <ProviderGUID>1</ProviderGUID>
      <ToolGUIDs>
        <GUID>89394f6c-c895-4d8b-8ced-a0864cdec1d7</GUID>
        <GUID>b3c7f2a1-4d8e-4f9b-a2c5-e6d1f0b3a8c4</GUID>
        <GUID>40051ada-ebee-4e40-8264-472186877f64</GUID>
        <GUID>f1a2b3c4-d5e6-4f7a-8b9c-0d1e2f3a4b5c</GUID>
        <GUID>a2b3c4d5-e6f7-4a8b-9c0d-1e2f3a4b5c6d</GUID>
      </ToolGUIDs>
      <DefaultSystemPrompt />
      <SystemPromptFile>scheduler-system-prompt.md</SystemPromptFile>
      <SamplePromptsFile>scheduler-sample-prompts.md</SamplePromptsFile>
    </AIAgentConfiguration>
    <AIAgentConfiguration>
      <GUID>c3d4e5f6-a7b8-4c9d-0e1f-2a3b4c5d6e7f</GUID>
      <Name>Data Analyst</Name>
      <Description>Answers data questions by running existing reports and exploring data sources read-only, summarizing results without modifying any report.</Description>
      <ProviderGUID>1</ProviderGUID>
      <ToolGUIDs>
        <GUID>21865749-3026-4f91-8b66-17d25cfc5d81</GUID>
        <GUID>c3f46643-52cc-4570-b580-c2b787bb4de9</GUID>
        <GUID>40051ada-ebee-4e40-8264-472186877f64</GUID>
        <GUID>5329983b-9c8a-4825-b51d-9a7fb4949b53</GUID>
        <GUID>d4e5f6a7-b8c9-4d0e-1f2a-3b4c5d6e7f80</GUID>
        <GUID>89394f6c-c895-4d8b-8ced-a0864cdec1d7</GUID>
        <GUID>b3c7f2a1-4d8e-4f9b-a2c5-e6d1f0b3a8c4</GUID>
        <GUID>1f2e3d4c-5b6a-4798-8c0d-1e2f3a4b5c6e</GUID>
      </ToolGUIDs>
      <DefaultSystemPrompt />
      <SystemPromptFile>analyst-system-prompt.md</SystemPromptFile>
      <SamplePromptsFile>analyst-sample-prompts.md</SamplePromptsFile>
    </AIAgentConfiguration>
    <AIAgentConfiguration>
      <GUID>d4e5f6a7-b8c9-4d0e-1f2a-3b4c5d6e7f81</GUID>
      <Name>System Admin</Name>
      <Description>Handles administration and troubleshooting: reads event, execution, and schedule logs, inspects reports and sources, and manages repository files.</Description>
      <ProviderGUID>1</ProviderGUID>
      <ToolGUIDs>
        <GUID>21865749-3026-4f91-8b66-17d25cfc5d81</GUID>
        <GUID>c3f46643-52cc-4570-b580-c2b787bb4de9</GUID>
        <GUID>40051ada-ebee-4e40-8264-472186877f64</GUID>
        <GUID>5329983b-9c8a-4825-b51d-9a7fb4949b53</GUID>
        <GUID>d4e5f6a7-b8c9-4d0e-1f2a-3b4c5d6e7f80</GUID>
        <GUID>e7d2c9a4-1b6f-4e83-9a2c-5f0d8b3e7c61</GUID>
        <GUID>c3b1942e-fa0b-48c5-84f1-dc19709d4e07</GUID>
        <GUID>89394f6c-c895-4d8b-8ced-a0864cdec1d7</GUID>
        <GUID>b3c7f2a1-4d8e-4f9b-a2c5-e6d1f0b3a8c4</GUID>
        <GUID>a8b9c0d1-e2f3-4a4b-5c6d-7e8f9a0b1c2d</GUID>
      </ToolGUIDs>
      <DefaultSystemPrompt />
      <SystemPromptFile>admin-system-prompt.md</SystemPromptFile>
      <SamplePromptsFile>admin-sample-prompts.md</SamplePromptsFile>
    </AIAgentConfiguration>
  </AIAgents>
</AIServerConfiguration>